glassknife/__init__.py
glassknife/common.py
glassknife/config.py
glassknife/make_indexes.py
glassknife/process_notes.py
glassknife-0.1.0.dist-info/entry_points.txt
glassknife-0.1.0.dist-info/LICENSE
glassknife-0.1.0.dist-info/WHEEL
glassknife-0.1.0.dist-info/METADATA
glassknife-0.1.0.dist-info/RECORD
