Metadata-Version: 2.1
Name: glassknife
Version: 0.1.0
Summary: Obsidian vault management tools
Home-page: https://github.com/kstrauser/glassknife
License: Apache 2.0
Author: Kirk Strauser
Author-email: kirk@strauser.com
Requires-Python: >=3.7,<4.0
Classifier: Development Status :: 3 - Alpha
Classifier: Intended Audience :: End Users/Desktop
Classifier: License :: OSI Approved :: Apache Software License
Classifier: License :: Other/Proprietary License
Classifier: Programming Language :: Python :: 3
Classifier: Programming Language :: Python :: 3.10
Classifier: Programming Language :: Python :: 3.7
Classifier: Programming Language :: Python :: 3.8
Classifier: Programming Language :: Python :: 3.9
Classifier: Topic :: Office/Business :: News/Diary
Classifier: Topic :: Text Processing :: Markup :: Markdown
Classifier: Topic :: Utilities
Requires-Dist: PyYAML (>=5.4.1,<6.0.0)
Requires-Dist: pydantic (>=1.8.2,<2.0.0)
Requires-Dist: xdg (>=5.1.1,<6.0.0)
Project-URL: Repository, https://github.com/kstrauser/glassknife.git
